treeshake/__init__.py
treeshake/__main__.py
treeshake/shaker.cpython-39-darwin.so
treeshake/stylesheet.cpython-39-darwin.so
treeshake-0.3.1.dist-info/LICENSE.md
treeshake-0.3.1.dist-info/METADATA
treeshake-0.3.1.dist-info/WHEEL
treeshake-0.3.1.dist-info/entry_points.txt
treeshake-0.3.1.dist-info/top_level.txt
treeshake-0.3.1.dist-info/RECORD
