Metadata-Version: 2.1
Name: treeshake
Version: 0.3.1
Summary: Remove unused css in Python projects with C-powered tree shaking.
Home-page: https://github.com/jackmanapp/treeshake/
Author: Job Veldhuis
Author-email: job@baukefrederik.me
License: UNKNOWN
Platform: UNKNOWN
Classifier: Development Status :: 4 - Beta
Classifier: Programming Language :: Python :: Implementation :: CPython
Classifier: Topic :: Utilities
Requires-Python: >=3.6
Requires-Dist: beautifulsoup4 (>=4.9.3)
Requires-Dist: cssutils (>=2.2.0)
Requires-Dist: colorama (>=0.4.4)
